spanning_cidr/__init__.py
spanning_cidr/core.py
spanning_cidr-0.1.4.dist-info/LICENSE
spanning_cidr-0.1.4.dist-info/WHEEL
spanning_cidr-0.1.4.dist-info/METADATA
spanning_cidr-0.1.4.dist-info/RECORD
